04-vending-machine-fsm/rtl/lab3_behav.v

module lab3_behavioral(
    input [1:0] x,
    input init,
    input clk,
    output reg dispense,
    output reg [1:0] change,
    output reg [1:0] q
);

    reg [1:0] next_q;

    always @ (posedge clk or negedge init) begin
        if(!init) q <= 2'b0;
        else q <= next_q;
    end

    always @(*) begin
        case(q)
            2'b00: begin
                change = 2'b00;
                dispense = 0;
                case(x)
                    2'b00: next_q = 2'b00;
                    2'b01: next_q = 2'b01;
                    2'b10: next_q = 2'b00;
                endcase
            end
            2'b01: begin
                case(x)
                    2'b00: begin
                        next_q = 2'b01;
                        change = 2'b00;
                        dispense = 0;
                    end
                    2'b01: begin
                        next_q = 2'b10;
                        change = 2'b00;
                        dispense = 0;
                    end
                    2'b10: begin
                        next_q = 2'b00;
                        change = 2'b01;
                        dispense = 0;
                    end
                endcase
            end
            2'b10: begin
                case(x)
                    2'b00: begin
                        next_q = 2'b00;
                        change = 2'b00;
                        dispense = 1;
                    end
                    2'b01: begin
                        next_q = 2'b10;
                        change = 2'b01;
                        dispense = 0;
                    end
                    2'b10: begin
                        next_q = 2'b00;
                        change = 2'b10;
                        dispense = 0;
                    end
                endcase
            end
            default: begin
                next_q = 2'b00;
                change = 2'b00;
                dispense = 0;
            end
        endcase
    end
endmodule

04-vending-machine-fsm/sim/behavioral/test_behav_vend_tb.v

module vend_behav_tb();

    initial begin
        $dumpfile("test_behav_vend_tb.vcd");
        $dumpvars(0, vend_behav_tb);
    end
    
    reg [1:0] x;
    reg init;
    reg clk;
    wire dispense;
    wire [1:0] change;
    wire [1:0] state;

    lab3_behavioral uut(.x(x), .init(init), .clk(clk), .dispense(dispense), .change(change), .q(state));

    always begin
        #5
        clk = ~clk;
    end

    localparam NICKEL = 2'b1;
    localparam SELECT = 2'b0;
    localparam COIN_RET = 2'b10;

    integer outfile;
    initial begin
        outfile = $fopen("out.txt", "w");
        $fdisplay(outfile, "\nTesting selecting water from states 01 and 10:\n");
        x = NICKEL;
        init = 1;
        clk = 0;
        #1
        init = 0;
        #5
        init = 1;
        x = NICKEL;
        #1
        $fdisplay(outfile, "State:    %b\tx: %b\tChange: %b\tDisp: %b\nExpected: %b\t   %b\t        %b\t      %b\n", 
            state, x, change, dispense,
            2'b0, x, 2'b0, 1'b0); 
        #9
        x = SELECT;
        #1
        $fdisplay(outfile, "State:    %b\tx: %b\tChange: %b\tDisp: %b\nExpected: %b\t   %b\t        %b\t      %b\n", 
            state, x, change, dispense,
            2'b1, x, 2'b0, 1'b0); 
        #9
        x = NICKEL;
        #1
        $fdisplay(outfile, "State:    %b\tx: %b\tChange: %b\tDisp: %b\nExpected: %b\t   %b\t        %b\t      %b\n", 
            state, x, change, dispense,
            2'b1, x, 2'b0, 1'b0); 
        #9
        x = NICKEL;
        #1
        $fdisplay(outfile, "State:    %b\tx: %b\tChange: %b\tDisp: %b\nExpected: %b\t   %b\t        %b\t      %b\n", 
            state, x, change, dispense,
            2'b10, x, 2'b01, 1'b0); 
        #9
        x = SELECT;
        #1
        $fdisplay(outfile, "State:    %b\tx: %b\tChange: %b\tDisp: %b\nExpected: %b\t   %b\t        %b\t      %b\n", 
            state, x, change, dispense,
            2'b10, x, 2'b0, 1'b1); 
        #9
        x = NICKEL;
        #1
        $fdisplay(outfile, "State:    %b\tx: %b\tChange: %b\tDisp: %b\nExpected: %b\t   %b\t        %b\t      %b\n", 
            state, x, change, dispense,
            2'b0, x, 2'b0, 1'b0); 
        #9

        $finish;
    end

endmodule

04-vending-machine-fsm/sim/behavioral/test_behav_vend_tb.vcd
$date
	Mon Nov 10 18:26:06 2025
$end
$version
	Icarus Verilog
$end
$timescale
	1ps
$end
$scope module vend_behav_tb $end
$var wire 2 ! state [1:0] $end
$var wire 1 " dispense $end
$var wire 2 # change [1:0] $end
$var parameter 2 $ COIN_RET $end
$var parameter 2 % NICKEL $end
$var parameter 2 & SELECT $end
$var reg 1 ' clk $end
$var reg 1 ( init $end
$var reg 2 ) x [1:0] $end
$var integer 32 * outfile [31:0] $end
$scope module uut $end
$var wire 1 ' clk $end
$var wire 1 ( init $end
$var wire 2 + x [1:0] $end
$var reg 2 , change [1:0] $end
$var reg 1 " dispense $end
$var reg 2 - next_q [1:0] $end
$var reg 2 . q [1:0] $end
$upscope $end
$upscope $end
$enddefinitions $end
$comment Show the parameter values. $end
$dumpall
b0 &
b1 %
b10 $
$end
#0
$dumpvars
bx .
b0 -
b0 ,
b1 +
b10000000000000000000000000000011 *
b1 )
1(
0'
b0 #
0"
bx !
$end
#1
b1 -
b0 !
b0 .
0(
#5
1'
#6
1(
#10
0'
#15
b0 -
b1 !
b1 .
1'
#16
b1 -
b0 )
b0 +
#20
0'
#25
1'
#26
b0 -
b1 )
b1 +
#30
0'
#35
b1 -
b0 !
b0 .
1'
#40
0'
#45
b0 -
b1 !
b1 .
1'
#46
b1 -
b0 )
b0 +
#50
0'
#55
1'
#56
b0 -
b1 )
b1 +
#60
0'
#65
b1 -
b0 !
b0 .
1'
